labinform/__init__.py
labinform/datasafe/__init__.py
labinform/datasafe/datasafe.py
labinform/eln/__init__.py
labinform/loi/__init__.py
tests/datasafe/__init__.py
tests/datasafe/test_datasafe.py
tests/eln/__init__.py
tests/loi/__init__.py
labinform-0.1.0.dev11.dist-info/LICENSE
labinform-0.1.0.dev11.dist-info/METADATA
labinform-0.1.0.dev11.dist-info/WHEEL
labinform-0.1.0.dev11.dist-info/top_level.txt
labinform-0.1.0.dev11.dist-info/RECORD
