Metadata-Version: 2.1
Name: labinform
Version: 0.1.0.dev11
Summary: Framework for reproducible research.
Home-page: https://www.labinform.de/
Author: Till Biskup
Author-email: till@till-biskup.de
License: UNKNOWN
Project-URL: Documentation, https://docs.labinform.de/
Project-URL: Source, https://github.com/tillbiskup/labinform
Keywords: Reproducible research,Electronic Lab Notebook,ELN
Platform: UNKNOWN
Classifier: Programming Language :: Python :: 3
Classifier: Programming Language :: Python :: 3.5
Classifier: Programming Language :: Python :: 3.6
Classifier: Programming Language :: Python :: 3.7
Classifier: License :: OSI Approved :: BSD License
Classifier: Operating System :: OS Independent
Classifier: Intended Audience :: Science/Research
Classifier: Development Status :: 3 - Alpha
Classifier: Topic :: Scientific/Engineering
Requires-Python: >=3.5
